README.md
setup.py
photodedup/__init__.py
photodedup/fileindex.py
photodedup/photodedup.py
photodedup.egg-info/PKG-INFO
photodedup.egg-info/SOURCES.txt
photodedup.egg-info/dependency_links.txt
photodedup.egg-info/entry_points.txt
photodedup.egg-info/requires.txt
photodedup.egg-info/top_level.txt