Metadata-Version: 1.0
Name: photodedup
Version: 0.2.1
Summary: A simple photo deduplication tool written in Python
Home-page: https://github.com/puyuan/photodedup
Author: Paul Yuan
Author-email: puyuan1@gmail.com
License: UNKNOWN
Keywords: photo dedup deduplication duplicate exif
Platform: UNKNOWN
